xlsxlite/__init__.py
xlsxlite/utils.py
xlsxlite/writer.py
xlsxlite/test/__init__.py
xlsxlite/test/base.py
xlsxlite/test/test_perf.py
xlsxlite/test/test_utils.py
xlsxlite/test/test_writer.py
xlsxlite-1.1.0.dist-info/METADATA
xlsxlite-1.1.0.dist-info/WHEEL
xlsxlite-1.1.0.dist-info/licenses/LICENSE
xlsxlite-1.1.0.dist-info/RECORD
