Metadata-Version: 2.4
Name: xlsxlite
Version: 1.1.0
Summary: Lightweight XLSX writer with emphasis on minimizing memory usage.
Project-URL: repository, http://github.com/nyaruka/xlsxlite
Author-email: TextIt <code@textit.com>
License: MIT
License-File: LICENSE
Classifier: Intended Audience :: Developers
Classifier: License :: OSI Approved :: MIT License
Classifier: Operating System :: OS Independent
Classifier: Programming Language :: Python
Requires-Python: >=3.10
